Metadata-Version: 1.2
Name: torch-trafo
Version: 0.1.0
Summary: PyTorch implementation of transformer block layers.
Home-page: UNKNOWN
Author: Ulf Hamster
Author-email: 554c46@gmail.com
License: Apache License 2.0
Platform: UNKNOWN
Requires-Python: >=3.6
